gitkat/__init__.py
gitkat/__main__.py
gitkat/_shim.py
gitkat-0.5.2.dist-info/licenses/LICENSE
gitkat-0.5.2.dist-info/METADATA
gitkat-0.5.2.dist-info/WHEEL
gitkat-0.5.2.dist-info/entry_points.txt
gitkat-0.5.2.dist-info/top_level.txt
gitkat-0.5.2.dist-info/RECORD
