Metadata-Version: 2.4
Name: gitkat
Version: 0.5.2
Summary: GitKat CLI (Rust binary)
Author: Aureuma
License: MIT
Project-URL: Homepage, https://github.com/Aureuma/GitKat
Project-URL: Repository, https://github.com/Aureuma/GitKat
Keywords: git,cli,rewrite
Classifier: License :: OSI Approved :: MIT License
Classifier: Programming Language :: Python :: 3
Classifier: Programming Language :: Python :: 3 :: Only
Classifier: Programming Language :: Python :: 3.8
Classifier: Programming Language :: Python :: 3.9
Classifier: Programming Language :: Python :: 3.10
Classifier: Programming Language :: Python :: 3.11
Classifier: Programming Language :: Python :: 3.12
Classifier: Programming Language :: Python :: 3.13
Classifier: Environment :: Console
Classifier: Operating System :: OS Independent
Requires-Python: >=3.8
License-File: LICENSE
Dynamic: license-file
